[
    {
      "question": "Quelle est la vitesse maximale sur une route à chaussées séparées hors agglomération pour un jeune conducteur en période probatoire ?",
      "options": [
        "80 km/h",
        "90 km/h",
        "100 km/h",
        "110 km/h"
      ],
      "correctAnswer": "100 km/h"
    },
    {
      "question": "Quel document doit toujours accompagner la carte grise pour justifier du contrôle technique ?",
      "options": [
        "La vignette Crit’Air",
        "Le procès-verbal du contrôle technique",
        "L’assurance du véhicule",
        "Le carnet d’entretien"
      ],
      "correctAnswer": "Le procès-verbal du contrôle technique"
    },
    {
      "question": "Que risque un conducteur qui téléphone en conduisant sans kit mains-libres ?",
      "options": [
        "Une amende et un retrait de points",
        "Aucune sanction",
        "Une immobilisation immédiate du véhicule",
        "Un simple avertissement sans frais"
      ],
      "correctAnswer": "Une amende et un retrait de points"
    },
    {
      "question": "Quel est le taux d’alcool maximal autorisé pour un jeune conducteur (en période probatoire) ?",
      "options": [
        "0,2 g/L",
        "0,5 g/L",
        "0,8 g/L",
        "1,0 g/L"
      ],
      "correctAnswer": "0,2 g/L"
    },
    {
      "question": "À partir de quel âge peut-on conduire une voiture sans permis (voiturette) en France ?",
      "options": [
        "14 ans",
        "16 ans",
        "18 ans",
        "21 ans"
      ],
      "correctAnswer": "14 ans"
    },
    {
      "question": "Que signifie un panneau carré bleu avec un « M » blanc ?",
      "options": [
        "Mairie à proximité",
        "Métro",
        "Mendicité interdite",
        "Médecin urgentiste"
      ],
      "correctAnswer": "Métro"
    },
    {
      "question": "Quel est le principal objectif de la ligne d'effet d'un feu tricolore ?",
      "options": [
        "Marquer l'arrêt si le feu est rouge",
        "Indiquer une zone de stationnement",
        "Signaler un changement de priorité",
        "Autoriser le franchissement du feu"
      ],
      "correctAnswer": "Marquer l'arrêt si le feu est rouge"
    },
    {
      "question": "Comment réagir en cas de fort vent latéral sur autoroute ?",
      "options": [
        "Accélérer pour stabiliser la trajectoire",
        "Maintenir fermement le volant et réduire la vitesse",
        "Freiner brusquement pour éviter la dérive",
        "Rouler sur la voie d’arrêt d’urgence"
      ],
      "correctAnswer": "Maintenir fermement le volant et réduire la vitesse"
    },
    {
      "question": "Quel est l'avantage d'une boîte automatique pour le conducteur ?",
      "options": [
        "Diminuer l'attention requise sur la route",
        "Ne plus freiner aux intersections",
        "Ne pas avoir à changer de vitesse manuellement",
        "Pouvoir rouler plus vite que la limite"
      ],
      "correctAnswer": "Ne pas avoir à changer de vitesse manuellement"
    },
    {
      "question": "En cas d'accident matériel sur autoroute, que faut-il faire en priorité ?",
      "options": [
        "Déplacer les véhicules en travers de la route",
        "Allumer les feux de détresse et enfiler le gilet de sécurité",
        "Quitter la chaussée sans feux de détresse",
        "Attendre la police au milieu de la voie"
      ],
      "correctAnswer": "Allumer les feux de détresse et enfiler le gilet de sécurité"
    },
    {
      "question": "Sur une route de montagne, comment croiser un véhicule qui monte alors que vous descendez ?",
      "options": [
        "Le véhicule qui monte doit reculer systématiquement",
        "C’est le plus gros véhicule qui passe en premier",
        "Le véhicule qui descend doit s’arrêter si nécessaire",
        "Les deux reculent jusqu’au prochain virage"
      ],
      "correctAnswer": "Le véhicule qui descend doit s’arrêter si nécessaire"
    },
    {
      "question": "Que signifie un feu rouge clignotant à un passage à niveau ?",
      "options": [
        "Passage autorisé en cas d’absence de train",
        "Arrêt absolu et immédiat",
        "Ralentir seulement",
        "Priorité aux véhicules sur rails"
      ],
      "correctAnswer": "Arrêt absolu et immédiat"
    },
    {
      "question": "Quel est l'objectif du permis AM (ex-BSR) ?",
      "options": [
        "Autoriser la conduite d’une moto de 125 cm³",
        "Autoriser la conduite d’un cyclomoteur ou quadricycle léger à moteur",
        "Autoriser la conduite d’une voiture dès 14 ans",
        "Remplacer le permis B"
      ],
      "correctAnswer": "Autoriser la conduite d’un cyclomoteur ou quadricycle léger à moteur"
    },
    {
      "question": "Quel équipement est obligatoire pour un motocycliste en France ?",
      "options": [
        "Des bottes homologuées",
        "Un gilet jaune fluo",
        "Un casque homologué et des gants",
        "Un extincteur"
      ],
      "correctAnswer": "Un casque homologué et des gants"
    },
    {
      "question": "Comment doit-on réagir face à un véhicule circulant à contresens sur autoroute ?",
      "options": [
        "Klaxonner longuement et continuer",
        "Freiner brutalement et faire demi-tour",
        "Signaler la situation aux autorités (112 ou 17) et adapter sa conduite",
        "Allumer les pleins phares et se mettre sur la bande d’arrêt d’urgence"
      ],
      "correctAnswer": "Signaler la situation aux autorités (112 ou 17) et adapter sa conduite"
    },
    {
      "question": "Quelle est la durée de validité du certificat d’examen du permis de conduire (CEPC) ?",
      "options": [
        "1 semaine",
        "2 semaines",
        "4 mois",
        "1 an"
      ],
      "correctAnswer": "4 mois"
    },
    {
      "question": "Quel est le délai pour immatriculer un véhicule d’occasion acquis en France ?",
      "options": [
        "48 heures",
        "1 semaine",
        "1 mois",
        "3 mois"
      ],
      "correctAnswer": "1 mois"
    },
    {
      "question": "Qu’est-ce que le « corridor de sécurité » sur autoroute ?",
      "options": [
        "Une voie dédiée aux piétons",
        "Une zone réservée aux poids lourds",
        "Un espace libre à laisser aux secours sur la voie de droite en cas d’accident",
        "Un couloir obligatoire pour les véhicules lents"
      ],
      "correctAnswer": "Un espace libre à laisser aux secours sur la voie de droite en cas d’accident"
    },
    {
      "question": "Quel est l’âge minimum pour obtenir le permis A2 (moto de puissance limitée) ?",
      "options": [
        "14 ans",
        "16 ans",
        "18 ans",
        "21 ans"
      ],
      "correctAnswer": "18 ans"
    },
    {
      "question": "Que signifie un panneau indiquant « Voie réservée Bus, Taxi, Vélo » ?",
      "options": [
        "Interdiction de circuler pour les voitures particulières",
        "Voie ouverte à tous sauf aux poids lourds",
        "Voie autorisée uniquement aux transports collectifs, taxis et vélos",
        "Voie en sens unique"
      ],
      "correctAnswer": "Voie autorisée uniquement aux transports collectifs, taxis et vélos"
    },
    {
      "question": "Dans quelles circonstances l’usage des feux de brouillard avant est-il autorisé ?",
      "options": [
        "Uniquement la nuit en ville",
        "En cas de pluie ou de brouillard épais, et sur routes étroites sinueuses",
        "Tout le temps",
        "Jamais, ils sont interdits"
      ],
      "correctAnswer": "En cas de pluie ou de brouillard épais, et sur routes étroites sinueuses"
    },
    {
      "question": "Quel est le temps de réaction moyen d’un conducteur en bonne condition ?",
      "options": [
        "0,2 seconde",
        "1 seconde",
        "2 secondes",
        "5 secondes"
      ],
      "correctAnswer": "1 seconde"
    },
    {
      "question": "Sur un rond-point, comment réagir si un piéton traverse la chaussée devant vous ?",
      "options": [
        "Le klaxonner pour qu’il se dépêche",
        "Le contourner si possible",
        "S’arrêter et le laisser passer",
        "Continuer, car la priorité n’est pas aux piétons sur un rond-point"
      ],
      "correctAnswer": "S’arrêter et le laisser passer"
    },
    {
      "question": "Quelle est la sanction pour un excès de vitesse de plus de 50 km/h au-dessus de la limite autorisée ?",
      "options": [
        "Un simple avertissement",
        "Retrait de 1 point et amende",
        "Amende importante, retrait de 6 points et confiscation possible du véhicule",
        "Aucune sanction"
      ],
      "correctAnswer": "Amende importante, retrait de 6 points et confiscation possible du véhicule"
    },
    {
      "question": "Que doit-on faire avant d’ouvrir la portière côté circulation ?",
      "options": [
        "Se fier au rétroviseur intérieur uniquement",
        "Rien, les autres usagers doivent faire attention",
        "Regarder dans le rétroviseur et l’angle mort (méthode Dutch Reach)",
        "Klaxonner pour prévenir"
      ],
      "correctAnswer": "Regarder dans le rétroviseur et l’angle mort (méthode Dutch Reach)"
    },
    {
      "question": "Quel est le risque principal d’un chargement mal arrimé sur un véhicule ?",
      "options": [
        "Augmenter la consommation de carburant",
        "Provoquer la chute d’objets sur la route et des accidents",
        "User plus rapidement les pneus",
        "Rendre le véhicule plus silencieux"
      ],
      "correctAnswer": "Provoquer la chute d’objets sur la route et des accidents"
    },
    {
      "question": "Quelle est la règle pour tourner à gauche dans un sens giratoire ?",
      "options": [
        "Ne pas mettre de clignotant",
        "Mettre le clignotant à gauche en entrant, puis à droite avant de sortir",
        "Rester sur la voie de droite",
        "Toujours klaxonner avant de sortir"
      ],
      "correctAnswer": "Mettre le clignotant à gauche en entrant, puis à droite avant de sortir"
    },
    {
      "question": "Quelle conséquence peut avoir une pression trop basse des pneus ?",
      "options": [
        "Aucune influence sur la conduite",
        "Allonger les distances de freinage et provoquer une surchauffe",
        "Améliorer l’adhérence sous la pluie",
        "Réduire la consommation de carburant"
      ],
      "correctAnswer": "Allonger les distances de freinage et provoquer une surchauffe"
    },
    {
      "question": "Quelle conduite adopter pour traverser un passage à gué ?",
      "options": [
        "Rouler vite pour évacuer l’eau",
        "S’arrêter au milieu pour mesurer la profondeur",
        "Rouler lentement et en régime bas pour éviter les vagues",
        "Ignorer le gué et faire demi-tour"
      ],
      "correctAnswer": "Rouler lentement et en régime bas pour éviter les vagues"
    },
    {
      "question": "Comment le point mort influence-t-il la direction d’un véhicule en descente ?",
      "options": [
        "Il améliore la direction",
        "Il rend la direction plus dure",
        "Il supprime le frein moteur et peut rendre le véhicule difficile à contrôler",
        "Il n’a aucune influence"
      ],
      "correctAnswer": "Il supprime le frein moteur et peut rendre le véhicule difficile à contrôler"
    },
    {
      "question": "À quel âge peut-on tracter une remorque de plus de 750 kg ?",
      "options": [
        "16 ans avec le permis B",
        "18 ans avec permis B et formation B96 ou permis BE selon le PTAC",
        "21 ans obligatoirement",
        "25 ans minimum"
      ],
      "correctAnswer": "18 ans avec permis B et formation B96 ou permis BE selon le PTAC"
    },
    {
      "question": "Quelle est la différence entre la ligne de rive et la bande d’arrêt d’urgence ?",
      "options": [
        "La ligne de rive est juste un marquage au sol, la bande d’arrêt d’urgence est réservée aux arrêts de détresse",
        "Elles désignent la même chose",
        "La bande d’arrêt d’urgence est réservée aux vélos",
        "La ligne de rive est interdite aux piétons"
      ],
      "correctAnswer": "La ligne de rive est juste un marquage au sol, la bande d’arrêt d’urgence est réservée aux arrêts de détresse"
    },
    {
      "question": "En cas de crevaison sur autoroute, que faut-il faire après s’être arrêté sur la bande d’arrêt d’urgence ?",
      "options": [
        "Rester dans la voiture",
        "Placer le triangle de présignalisation à environ 30 m et se mettre derrière la glissière",
        "Téléphoner à l’assureur sans sortir",
        "Attendre la police pour changer la roue"
      ],
      "correctAnswer": "Placer le triangle de présignalisation à environ 30 m et se mettre derrière la glissière"
    },
    {
      "question": "Quelle est la validité d’un contrôle technique pour une voiture particulière de plus de 4 ans ?",
      "options": [
        "1 an",
        "2 ans",
        "3 ans",
        "5 ans"
      ],
      "correctAnswer": "2 ans"
    },
    {
      "question": "Que signifie un panneau carré bleu avec un pictogramme de stationnement barré d'une diagonale rouge ?",
      "options": [
        "Stationnement interdit mais arrêt autorisé",
        "Fin de zone de stationnement réglementé",
        "Stationnement autorisé la nuit uniquement",
        "Début de zone à stationnement gratuit"
      ],
      "correctAnswer": "Fin de zone de stationnement réglementé"
    },
    {
      "question": "Que faire si vous roulez sur une voie rapide et apercevez un bouchon ?",
      "options": [
        "Freiner brusquement et mettre les warnings",
        "Rester sur sa voie, ralentir progressivement et allumer les feux de détresse",
        "Changer de voie immédiatement",
        "Accélérer pour doubler le bouchon"
      ],
      "correctAnswer": "Rester sur sa voie, ralentir progressivement et allumer les feux de détresse"
    },
    {
      "question": "Que doit faire un conducteur avant de dépasser un vélo sur une route sans marquage ?",
      "options": [
        "Klaxonner pour l’avertir",
        "Garder seulement 50 cm de distance latérale",
        "Dépasser en laissant 1 m en agglomération et 1,5 m hors agglo",
        "Lui demander de s’arrêter"
      ],
      "correctAnswer": "Dépasser en laissant 1 m en agglomération et 1,5 m hors agglo"
    },
    {
      "question": "Quel est l’objectif du « Sauvetage rapide » en cas d’accident ?",
      "options": [
        "Sortir la victime du véhicule sans précaution",
        "Protéger, Alerter, Secourir (P.A.S.)",
        "Appeler un proche pour assistance",
        "Enlever le véhicule de la route au plus vite"
      ],
      "correctAnswer": "Protéger, Alerter, Secourir (P.A.S.)"
    },
    {
      "question": "Quelle est la sanction pour un refus de priorité ayant entraîné un accident ?",
      "options": [
        "Aucune sanction",
        "Retrait de 1 point et avertissement",
        "Retrait de 4 points et amende",
        "Prison ferme"
      ],
      "correctAnswer": "Retrait de 4 points et amende"
    },
    {
      "question": "En cas de panne de feux stop, que faut-il faire provisoirement pour signaler un freinage ?",
      "options": [
        "Continuer normalement",
        "Utiliser le klaxon",
        "Utiliser les feux de détresse pour avertir",
        "Arrêter de freiner"
      ],
      "correctAnswer": "Utiliser les feux de détresse pour avertir"
    }
  ]
  